{
    "subjects": [
        {
            "1楼": [
                "https://gsp0.baidu.com/5aAHeD3nKhI2p27j8IqW0jdnxx1xbK/tb/editor/images/client/image_emoticon66.png",
                "http://tiebapic.baidu.com/forum/w%3D580/sign=7e09c099958ba61edfeec827713597cc/9bbaf2198618367a1588b98e39738bd4b21ce548.jpg"
            ]
        },
        {
            "2楼": "贴吧官方都认为是卧薪尝胆，不算违规，还让以前吧主求现在吧主，还挣扎什么。"
        },
        {
            "3楼": [
                "https://gsp0.baidu.com/5aAHeD3nKhI2p27j8IqW0jdnxx1xbK/tb/editor/images/client/image_emoticon25.png"
            ]
        },
        {
            "4楼": "+3"
        },
        {
            "5楼": "。。。"
        },
        {
            "6楼": [
                "https://gsp0.baidu.com/5aAHeD3nKhI2p27j8IqW0jdnxx1xbK/tb/editor/images/client/image_emoticon25.png",
                "https://gsp0.baidu.com/5aAHeD3nKhI2p27j8IqW0jdnxx1xbK/tb/editor/images/client/image_emoticon25.png"
            ]
        },
        {
            "7楼": "正道的光"
        },
        {
            "8楼": [
                "http://tiebapic.baidu.com/forum/w%3D580/sign=4c2922abb086c91708035231f93c70c6/8a608dd6277f9e2fdeebdb5b0830e924ba99f3f7.jpg"
            ]
        },
        {
            "9楼": [
                "https://gsp0.baidu.com/5aAHeD3nKhI2p27j8IqW0jdnxx1xbK/tb/editor/images/client/image_emoticon1.png"
            ]
        },
        {
            "10楼": "+1"
        },
        {
            "11楼": "牛"
        },
        {
            "12楼": "贴吧官方牛逼"
        },
        {
            "13楼": [
                "https://gsp0.baidu.com/5aAHeD3nKhI2p27j8IqW0jdnxx1xbK/tb/editor/images/client/image_emoticon13.png",
                "https://gsp0.baidu.com/5aAHeD3nKhI2p27j8IqW0jdnxx1xbK/tb/editor/images/client/image_emoticon13.png"
            ]
        },
        {
            "14楼": [
                "https://gsp0.baidu.com/5aAHeD3nKhI2p27j8IqW0jdnxx1xbK/tb/editor/images/client/image_emoticon66.png"
            ]
        },
        {
            "15楼": [
                "https://gsp0.baidu.com/5aAHeD3nKhI2p27j8IqW0jdnxx1xbK/tb/editor/images/client/image_emoticon25.png"
            ]
        },
        {
            "16楼": "去火拳艾斯那看了下，浓重的饭圈恶臭"
        },
        {
            "17楼": [
                "http://tiebapic.baidu.com/forum/w%3D580/sign=aee7b3789001a18bf0eb1247ae2e0761/86df5382b2b7d0a229c731c9dcef76094a369a46.jpg"
            ]
        },
        {
            "18楼": "微博贴吧官方纯粹是糊的"
        },
        {
            "19楼": "哈"
        },
        {
            "20楼": "慕名前来，别的不说，新吧主牛逼"
        },
        {
            "21楼": [
                "http://tiebapic.baidu.com/forum/w%3D580/sign=e3f292584cb5c9ea62f303ebe538b622/a960ac1ea8d3fd1f965d0669274e251f94ca5f7c.jpg",
                "http://tiebapic.baidu.com/forum/w%3D580/sign=23cb9d9726adcbef01347e0e9cae2e0e/d7e89845d688d43f74fd35a16a1ed21b0ff43b7c.jpg",
                "http://tiebapic.baidu.com/forum/w%3D580/sign=eb7b018c61c6a7efb926a82ecdfbafe9/b5ba05b30f2442a7d55959f6c643ad4bd013027c.jpg",
                "http://tiebapic.baidu.com/forum/w%3D580/sign=e0d5fde2970a19d8cb03840d03fb82c9/dde8798da97739129f712132ef198618377ae27d.jpg",
                "http://tiebapic.baidu.com/forum/w%3D580/sign=b3690326c188d43ff0a991fa4d1fd2aa/3a34a3ec8a1363272dba6660868fa0ec09fac77d.jpg",
                "http://tiebapic.baidu.com/forum/w%3D580/sign=29cd4850df95d143da76e42b43f18296/d9f4b4096b63f624000a9d509044ebf81b4ca37d.jpg"
            ]
        },
        {
            "22楼": "也就是哪有热闹往哪凑，拿你们骗流量，都恨不得把事情闹大，他们在乎的不是解决方法，而是怎样闹得更大骗流量"
        },
        {
            "23楼": [
                "https://gsp0.baidu.com/5aAHeD3nKhI2p27j8IqW0jdnxx1xbK/tb/editor/images/client/image_emoticon25.png"
            ]
        },
        {
            "24楼": "就这戏码给翡翠台能拍多一个溏心风暴出来"
        },
        {
            "25楼": [
                "https://gsp0.baidu.com/5aAHeD3nKhI2p27j8IqW0jdnxx1xbK/tb/editor/images/client/image_emoticon25.png"
            ]
        },
        {
            "26楼": "这种事情见得多了，我只想说懂得都懂，不懂的我也不多解释，毕竟自己知道就好，细细品吧。你们也别来问我怎么了，利益牵扯太大，说了对你我都没好处，当不知道就行了，其余的我只能说这里面水很深，牵扯到很多东西。详细情况你们自己是很难找的，网上大部分已经删除干净了，所以我只能说懂得都懂。懂的人已经基本都获利上岸什么的了，不懂的人永远不懂，关键懂的人都是自己悟的，你也不知道谁是懂的人也没法请教，大家都藏着掖着生怕别人知道自己懂事，懂了就能收割不懂的，你甚至都不知道自己不懂。只是在有些时候，某些人对某些事情不懂装懂，还以为别人不懂。其实自己才是不懂的，别人懂的够多了，不仅懂，还懂的超越了这个范围，但是某些不懂的人让这个懂的人完全教不懂，所以不懂的人永远不懂，只能不懂装懂，别人说懂的都懂，只要点点头就行了，懂了吗？这种事情见得多了，我只想说懂得都懂，不懂的我也不多解释，毕竟自己知道就好，细细品吧。你们也别来问我怎么了，利益牵扯太大，说了对你我都没好处，当不知道就行了，其余的我只能说这里面水很深，牵扯到很多东西。详细情况你们自己是很难找的，网上大部分已经删除干净了，所以我只能说懂得都懂。懂的人已经基本都获利上岸什么的了，不懂的人永远不懂，关键懂的人都是自己悟的，你也不知道谁是懂的人也没法请教，大家都藏着掖着生怕别人知道自己懂事，懂了就能收割不懂的，你甚至都不知道自己不懂。只是在有些时候，某些人对某些事情不懂装懂，还以为别人不懂。其实自己才是不懂的，别人懂的够多了，不仅懂，还懂的超越了这个范围，但是某些不懂的人让这个懂的人完全教不懂，所以不懂的人永远不懂，只能不懂装懂，别人说懂的都懂，只要点点头就行了，懂了吗？这种事情见得多了，我只想说懂得都懂，不懂的我也不多解释，毕竟自己知道就好，细细品吧。你们也别来问我怎么了，利益牵扯太大，说了对你我都没好处，当不知道就行了，其余的我只能说这里面水很深，牵扯到很多东西。详细情况你们自己是很难找的，网上大部分已经删除干净了，所以我只能说懂得都懂。懂的人已经基本都获利上岸什么的了，不懂的人永远不懂，关键懂的人都是自己悟的，你也不知道谁是懂的人也没法请教，大家都藏着掖着生怕别人知道自己懂事，懂了就能收割不懂的，你甚至都不知道自己不懂。只是在有些时候，某些人对某些事情不懂装懂，还以为别人不懂。其实自己才是不懂的，别人懂的够多了，不仅懂，还懂的超越了这个范围，"
        },
        {
            "27楼": "前任吧主态度好一点的话起码能把帖子搬运过去，四处乱跳换谁也反感"
        },
        {
            "28楼": [
                "http://tiebapic.baidu.com/forum/w%3D580/sign=a94a8260868fa0ec7fc764051696594a/ce36ed1190ef76c66c75bb788a16fdfaae51672d.jpg"
            ]
        },
        {
            "29楼": "给钱了？"
        },
        {
            "30楼": "？？？？人家目前也没违规呀。。。不符合这个吧的，删了又如何，又不是说乱删。。。假设你放生吧宣传，你看人家关不关小黑屋。"
        }
    ]
}